shop/BinaryTree.py
shop/Filter.py
shop/Infix_to_Polish.py
shop/Parsers.py
shop/Query.py
shop/Record.py
shop/Shop.py
shop/__init__.py
ShopFilteringToolInect-0.0.1.dist-info/LICENSE.txt
ShopFilteringToolInect-0.0.1.dist-info/METADATA
ShopFilteringToolInect-0.0.1.dist-info/WHEEL
ShopFilteringToolInect-0.0.1.dist-info/top_level.txt
ShopFilteringToolInect-0.0.1.dist-info/RECORD
